<lcgdict>
  <class name="PixelJet"/>
  <class name="std::vector<PixelJet>"/>
  <class name="edm::Wrapper<std::vector<PixelJet> >"/>
  <class name="std::vector<PixelJet>::const_iterator"/>
  <class name="edm::Wrapper<std::vector<PixelJet>::const_iterator >"/>
  <class name="std::vector<PixelJet>::iterator"/>
  <class name="edm::Wrapper<std::vector<PixelJet>::iterator >"/>
  <class name="edm::RefProd<std::vector<PixelJet> >"/>
  <class name="edm::Ref<std::vector<PixelJet>,PixelJet,edm::refhelper::FindUsingAdvance<std::vector<PixelJet>,PixelJet> >"/>
  <class name="edm::Wrapper<edm::Ref<std::vector<PixelJet>,PixelJet,edm::refhelper::FindUsingAdvance<std::vector<PixelJet>,PixelJet> > >"/>
  <class name="edm::RefVector<std::vector<PixelJet>,PixelJet,edm::refhelper::FindUsingAdvance<std::vector<PixelJet>,PixelJet> >"/>
  <class name="edm::Wrapper<edm::RefVector<std::vector<PixelJet>,PixelJet,edm::refhelper::FindUsingAdvance<std::vector<PixelJet>,PixelJet> > >"/>
</lcgdict>
